README.txt
setup.py
stompest/__init__.py
stompest.async.egg-info/PKG-INFO
stompest.async.egg-info/SOURCES.txt
stompest.async.egg-info/dependency_links.txt
stompest.async.egg-info/namespace_packages.txt
stompest.async.egg-info/requires.txt
stompest.async.egg-info/top_level.txt
stompest.async.egg-info/zip-safe
stompest/async/__init__.py
stompest/async/client.py
stompest/async/listener.py
stompest/async/protocol.py
stompest/async/util.py
stompest/async/examples/__init__.py
stompest/async/examples/consumer.py
stompest/async/examples/producer.py
stompest/async/examples/transformer.py
stompest/async/tests/__init__.py
stompest/async/tests/async_client_integration_test.py
stompest/async/tests/async_client_test.py
stompest/async/tests/async_util_test.py
stompest/async/tests/broker_simulator.py