Metadata-Version: 1.1
Name: stompest.async
Version: 2.1.2
Summary: Twisted STOMP client based upon the stompest API.
Home-page: https://github.com/nikipore/stompest
Author: Jan Mueller
Author-email: nikipore@gmail.com
License: Apache License 2.0
Keywords: stomp twisted activemq rabbitmq apollo
Platform: UNKNOWN
Classifier: Development Status :: 5 - Production/Stable
Classifier: Framework :: Twisted
Classifier: Topic :: System :: Networking
Classifier: Operating System :: OS Independent
Classifier: License :: OSI Approved :: Apache Software License
Classifier: Intended Audience :: Developers
Classifier: Programming Language :: Python
Classifier: Topic :: Software Development :: Libraries :: Python Modules
